gpgkeys/__init__.py
gpgkeys/__main__.py
gpgkeys/config.py
gpgkeys/gpgkeys.py
gpgkeys/parser.py
gpgkeys/scanner.py
gpgkeys/splitter.py
gpgkeys/testing.py
gpgkeys/utils.py
gpgkeys/completions/__init__.py
gpgkeys/completions/key.py
gpgkeys/completions/keyserver.py
gpgkeys-2.2.dist-info/LICENSE
gpgkeys-2.2.dist-info/METADATA
gpgkeys-2.2.dist-info/WHEEL
gpgkeys-2.2.dist-info/entry_points.txt
gpgkeys-2.2.dist-info/top_level.txt
gpgkeys-2.2.dist-info/RECORD
