Metadata-Version: 2.1
Name: gpgkeys
Version: 2.2
Summary: A GnuPG Shell
Home-page: https://github.com/stefanholek/gpgkeys
Author: Stefan H. Holek
Author-email: stefan@epy.co.at
License: GPLv3
Project-URL: Documentation, https://gpgkeys.readthedocs.io/en/stable/
Keywords: gnupg,gpg,gpg2,front-end,gpg shell,shell,REPL
Classifier: Development Status :: 5 - Production/Stable
Classifier: Environment :: Console
Classifier: Intended Audience :: End Users/Desktop
Classifier: Intended Audience :: System Administrators
Classifier: License :: OSI Approved :: GNU General Public License v3 (GPLv3)
Classifier: Operating System :: MacOS :: MacOS X
Classifier: Operating System :: POSIX
Classifier: Programming Language :: Python
Classifier: Programming Language :: Python :: 2
Classifier: Programming Language :: Python :: 3
Classifier: Programming Language :: Python :: Implementation :: CPython
License-File: LICENSE
Requires-Dist: setuptools
Requires-Dist: rl (>=3.1)
Requires-Dist: kmd (>=2.4)
Requires-Dist: term (>=2.4)
Provides-Extra: docs
Requires-Dist: sphinx (==5.3.0) ; extra == 'docs'
Requires-Dist: sphinx-rtd-theme (==1.0.0) ; extra == 'docs'
